Metadata-Version: 1.2
Name: conflictwatch
Version: 0.0.2
Summary: Check all remote branches against your current HEAD and staging
Home-page: https://github.com/alisternorris/conflictwatch
Author: Alister Norris
Author-email: hi@alisternorris.com
License: MIT
Platform: UNKNOWN
Classifier: License :: OSI Approved :: MIT License
Classifier: Programming Language :: Python
Classifier: Programming Language :: Python :: 3
Classifier: Programming Language :: Python :: 3.6
Classifier: Programming Language :: Python :: Implementation :: CPython
Classifier: Programming Language :: Python :: Implementation :: PyPy
Requires-Python: >=3.6.0
